pymetawear/__init__.py
pymetawear/client.py
pymetawear/discover.py
pymetawear/exceptions.py
pymetawear/version.py
pymetawear/modules/__init__.py
pymetawear/modules/accelerometer.py
pymetawear/modules/ambientlight.py
pymetawear/modules/barometer.py
pymetawear/modules/base.py
pymetawear/modules/gpio.py
pymetawear/modules/gyroscope.py
pymetawear/modules/haptic.py
pymetawear/modules/led.py
pymetawear/modules/magnetometer.py
pymetawear/modules/sensorfusion.py
pymetawear/modules/settings.py
pymetawear/modules/switch.py
pymetawear/modules/temperature.py
pymetawear-0.12.0.dist-info/AUTHORS.rst
pymetawear-0.12.0.dist-info/LICENSE
pymetawear-0.12.0.dist-info/METADATA
pymetawear-0.12.0.dist-info/WHEEL
pymetawear-0.12.0.dist-info/top_level.txt
pymetawear-0.12.0.dist-info/RECORD
