Metadata-Version: 2.1
Name: pymetawear
Version: 0.12.0
Summary: Python client for connecting to MbientLab's MetaWear boards
Home-page: https://github.com/hbldh/pymetawear
Author: Henrik Blidh
Author-email: henrik.blidh@nedomkull.com
License: MIT
Platform: UNKNOWN
Classifier: License :: OSI Approved :: MIT License
Classifier: Programming Language :: Python :: 2.7
Classifier: Programming Language :: Python :: 3.4
Classifier: Programming Language :: Python :: 3.5
Classifier: Programming Language :: Python :: 3.6
Classifier: Operating System :: POSIX :: Linux
Classifier: Development Status :: 4 - Beta
Classifier: Intended Audience :: Developers
Requires-Dist: metawear (==0.7.0)
Requires-Dist: tqdm
